README.md
setup.cfg
setup.py
subrake/__init__.py
subrake/__main__.py
subrake/parser.py
subrake/pull.py
subrake/round.py
subrake.egg-info/PKG-INFO
subrake.egg-info/SOURCES.txt
subrake.egg-info/dependency_links.txt
subrake.egg-info/entry_points.txt
subrake.egg-info/requires.txt
subrake.egg-info/top_level.txt
subrake/handlers/__init__.py
subrake/handlers/ask.py
subrake/handlers/baidu.py
subrake/handlers/bing.py
subrake/handlers/crt.py
subrake/handlers/dnsdumpster.py
subrake/handlers/google.py
subrake/handlers/netcraft.py
subrake/handlers/threatcrowd.py
subrake/handlers/virustotal.py
subrake/handlers/yahoo.py