Metadata-Version: 2.1
Name: subrake
Version: 3.3
Summary: A Subdomain Enumeration and Validation tool for Bug Bounty and Pentesters.
Home-page: https://github.com/hash3liZer/Subrake
Author: hash3liZer
Author-email: sheikhshameerkashif@protonmail.com
License: GPLv3
Download-URL: https://github.com/hash3liZer/Subrake/archive/v3.3.tar.gz
Keywords: bugbounty,bugbountytips,tool,subdomain,pentesting
Platform: UNKNOWN
Classifier: License :: OSI Approved :: GNU General Public License v3 (GPLv3)
Classifier: Programming Language :: Python :: 3
Classifier: Programming Language :: Python :: 3.8
Classifier: Development Status :: 5 - Production/Stable
Classifier: Operating System :: POSIX
